<?xml version="1.0" encoding="utf-8"?>
<UserCollection xmlns:xsi="http://www.w3.org/2001/XMLSchema-instance" xmlns:xsd="http://www.w3.org/2001/XMLSchema">
  <Users>
    <User>
      <Username>1</Username>
      <Password>fn5g+xrZS7Ud7B8EBFfuxg==</Password>
      <CurrentPosX>1300</CurrentPosX>
      <CurrentPosY>-200</CurrentPosY>
      <CurrentIsland>B</CurrentIsland>
      <TotalScore>301</TotalScore>
      <IslandA>
        <FillInTheBlanks>
          <FIB>
            <Index>1</Index>
            <Score>70</Score>
          </FIB>
          <FIB>
            <Index>2</Index>
          </FIB>
        </FillInTheBlanks>
        <WordGames>
          <Game>
            <Index>1</Index>
            <Word1>T</Word1>
            <Word2>F</Word2>
            <Word3>T</Word3>
            <Word3>F</Word3>
            <Word4>T</Word4>
            <Word5>T</Word5>
            <Word6>T</Word6>
            <Word7>T</Word7>
            <Word8>T</Word8>
            <Score>40</Score>
          </Game>
          <Game>
            <Index>2</Index>
          </Game>
        </WordGames>
        <Stories>
          <Story>1</Story>
        </Stories>
      </IslandA>
    </User>
    <User>
      <Username>Username</Username>
      <Password>zu9DpO2NoTBvPoWX1qcZGg==</Password>
      <CurrentPosX>830</CurrentPosX>
      <CurrentPosY>-30</CurrentPosY>
      <CurrentIsland>B</CurrentIsland>
      <TotalScore>300</TotalScore>
      <IslandA>
        <WordGames>
          <Game>
            <Index>1</Index>
            <Word1>T</Word1>
            <Word2>F</Word2>
            <Word3>T</Word3>
            <Word4>F</Word4>
            <Word5>T</Word5>
            <Word6>F</Word6>
            <Word7>T</Word7>
            <Word8>F</Word8>
            <Score>60</Score>
          </Game>
        </WordGames>
        <FillInTheBlanks>
          <FIB>
            <Index>1</Index>
          </FIB>
        </FillInTheBlanks>
      </IslandA>
    </User>
    <User>
      <Username>6546</Username>
      <Password>e42PGXVcV3+HCF3GO+7gzA==</Password>
      <CurrentPosX>-1592.712</CurrentPosX>
      <CurrentPosY>-208.3593</CurrentPosY>
      <CurrentIsland>A</CurrentIsland>
      <TotalScore>0</TotalScore>
    </User>
    <User>
      <Username>666</Username>
      <Password>wafL0c6dgmOU1+6Ye4LBkQ==</Password>
      <CurrentPosX>-793.2623</CurrentPosX>
      <CurrentPosY>273.5483</CurrentPosY>
      <CurrentIsland>A</CurrentIsland>
      <TotalScore>0</TotalScore>
      <IslandA>
        <FillInTheBlanks>
          <FIB>
            <Index>1</Index>
          </FIB>
        </FillInTheBlanks>
      </IslandA>
    </User>
    <User>
      <Username>123</Username>
      <Password>srwfzn5PzJQ9Gzx8a0HFgA==</Password>
      <CurrentPosX>845.2677</CurrentPosX>
      <CurrentPosY>91.24516</CurrentPosY>
      <CurrentIsland>B</CurrentIsland>
      <TotalScore>600</TotalScore>
      <IslandB>
        <FillInTheBlanks>
          <FIB>
            <Index>1</Index>
          </FIB>
        </FillInTheBlanks>
      </IslandB>
      <IslandA>
        <FillInTheBlanks>
          <FIB>
            <Index>1</Index>
            <Score>70</Score>
          </FIB>
          <FIB>
            <Index>2</Index>
          </FIB>
        </FillInTheBlanks>
        <WordGames>
          <Game>
            <Index>1</Index>
            <Word1>T</Word1>
            <Word2>F</Word2>
            <Word3>T</Word3>
            <Word3>F</Word3>
            <Word4>T</Word4>
            <Word5>T</Word5>
            <Word6>T</Word6>
            <Word7>T</Word7>
            <Word8>T</Word8>
            <Score>40</Score>
          </Game>
          <Game>
            <Index>2</Index>
          </Game>
        </WordGames>
        <Stories>
          <Story>1</Story>
        </Stories>
      </IslandA>
    </User>
  </Users>
</UserCollection>